MANIFEST.in
setup.py
code/__init__.py
sample_app_arvind.egg-info/PKG-INFO
sample_app_arvind.egg-info/SOURCES.txt
sample_app_arvind.egg-info/dependency_links.txt
sample_app_arvind.egg-info/not-zip-safe
sample_app_arvind.egg-info/requires.txt
sample_app_arvind.egg-info/top_level.txt