Metadata-Version: 1.0
Name: sample-app-arvind
Version: 0.2.2
Summary: The funniest joke in the world
Home-page: http://github.com/storborg/funniest
Author: Flying Circus
Author-email: flyingcircus@example.com
License: MIT
Platform: UNKNOWN
